odoo/addons/partner_shipping_policy/README.rst
odoo/addons/partner_shipping_policy/__init__.py
odoo/addons/partner_shipping_policy/__manifest__.py
odoo/addons/partner_shipping_policy/i18n/da_DK.po
odoo/addons/partner_shipping_policy/i18n/it.po
odoo/addons/partner_shipping_policy/i18n/partner_shipping_policy.pot
odoo/addons/partner_shipping_policy/models/__init__.py
odoo/addons/partner_shipping_policy/models/res_partner.py
odoo/addons/partner_shipping_policy/models/sale_order.py
odoo/addons/partner_shipping_policy/readme/CONTRIBUTORS.md
odoo/addons/partner_shipping_policy/readme/DESCRIPTION.md
odoo/addons/partner_shipping_policy/readme/USAGE.md
odoo/addons/partner_shipping_policy/static/description/icon.png
odoo/addons/partner_shipping_policy/static/description/index.html
odoo/addons/partner_shipping_policy/tests/__init__.py
odoo/addons/partner_shipping_policy/tests/test_partner_shipping_policy.py
odoo/addons/partner_shipping_policy/views/res_partner_views.xml
odoo_addon_partner_shipping_policy-18.0.1.0.0.2.dist-info/METADATA
odoo_addon_partner_shipping_policy-18.0.1.0.0.2.dist-info/WHEEL
odoo_addon_partner_shipping_policy-18.0.1.0.0.2.dist-info/top_level.txt
odoo_addon_partner_shipping_policy-18.0.1.0.0.2.dist-info/RECORD
